onoprienko221321KR/__init__.py
onoprienko221321KR/database.py
onoprienko221321KR-0.1.dist-info/METADATA
onoprienko221321KR-0.1.dist-info/WHEEL
onoprienko221321KR-0.1.dist-info/top_level.txt
onoprienko221321KR-0.1.dist-info/RECORD
