Metadata-Version: 2.1
Name: onoprienko221321KR
Version: 0.1
Summary: A library for interacting with a PostgreSQL database for medical inventory management
Home-page: https://github.com/yourusername/onoprienko221321KR
Author: Your Name
Author-email: your.email@example.com
License: UNKNOWN
Platform: UNKNOWN
Classifier: Programming Language :: Python :: 3
Classifier: License :: OSI Approved :: MIT License
Classifier: Operating System :: OS Independent
Requires-Python: >=3.6
Requires-Dist: psycopg2
